Metadata-Version: 2.0
Name: opan
Version: 0.4rc1
Summary: Open Anharmonic -- A computational chemistry toolkit
Home-page: https://www.github.com/bskinn/opan
Author: Brian Skinn
Author-email: bskinn@alum.mit.edu
License: The MIT License
Platform: UNKNOWN
Classifier: License :: OSI Approved :: MIT License
Classifier: Natural Language :: English
Classifier: Intended Audience :: Science/Research
Classifier: Operating System :: OS Independent
Classifier: Programming Language :: Python :: 3 :: Only
Classifier: Programming Language :: Python :: 3.4
Classifier: Programming Language :: Python :: 3.5
Classifier: Development Status :: 3 - Alpha
Classifier: Topic :: Scientific/Engineering :: Chemistry
Requires: numpy (>=1.10)
Requires: scipy (>=0.12)
Requires: h5py (>=2.4)
Provides: opan
